gempaterkini/__init__.py
latest_earthquake_in_Indonesia_2022-0.1.dist-info/LICENSE
latest_earthquake_in_Indonesia_2022-0.1.dist-info/METADATA
latest_earthquake_in_Indonesia_2022-0.1.dist-info/WHEEL
latest_earthquake_in_Indonesia_2022-0.1.dist-info/top_level.txt
latest_earthquake_in_Indonesia_2022-0.1.dist-info/RECORD
