Metadata-Version: 2.1
Name: latest-earthquake-in-Indonesia-2022
Version: 0.1
Summary: This package will get the latest 
Home-page: https://github.com/Learn-Python-Dev-Indonesia/latest-earthquake-in-indonesia
Author: Viko Aldi 
Author-email: piccoaldi@gmail.com
Project-URL: Website , https://github.com/viko-aldi
Classifier: Programming Language :: Python :: 3
Classifier: License :: OSI Approved :: GNU General Public License v3 (GPLv3)
Classifier: Operating System :: OS Independent
Classifier: Development Status :: 5 - Production/Stable
Requires-Python: >=3.6
License-File: LICENSE
